Workbook

Sheet Примеры
A1: text | B1: group | C1: label | D1: lang
A2: #Selling #Payment Kunga — licensed PSP 89% approval rate | Any industry | Fast Onboarding | T+0 **Local Accounts:** EEUU 🇺🇸, EU (LUX) 🇪🇺, UK 🇬🇧, MX 🇲🇽, CO 🇨🇴, BRA (PIX) 🇧🇷 , AR 🇦🇷 SEPA / SWIFT | B2: A1 | C2: 1 | D2: en
A3: #selling #Payment Psp for FTD! Ftd details EU Retention iban solution De iban ( local),Gb,LU,LT, viban FR | B3: A1 | C3: 1 | D3: en
A4: #selling #Payment Psp for ftds! 90%+ approval - au, NZ, eu and more 👌 Weekly settlements , instant setup✅✅✅ DM for more information‼️ | B4: A1 | C4: 1 | D4: en
A5: Всем привет! #Gmatch Меня зовут Арда, я сооснователь платежного решения Flux Finans. Мы предоставляем стабильные платежные решения для турецкого рынка с минимальными чеками 100/250/500/1000 TL и Conversion Rate 92,7–94,6%. На GGate будем рады познакомиться с мерчантами, PSP-провайдерами и агентами для долгосрочного сотрудничества. Для новых партнеров с конференции — специальные условия и дополнительная скидка. Пишите в личные сообщения, до встречи! | B5: A1 | C5: 1 | D5: ru
A6: Всем привет! Мы предоставляем стабильные платежные решения для турецкого рынка с минимальными чеками: 100 TL (индивидуальный запрос) 500 TL 1000 TL Conversion Rate 92,7–94,6%. Пишите в личные сообщения! | B6: A1 | C6: 1 | D6: ru
A7: #selling worldwide tier 1 psp good approve rate many local apms (europe asia africa latam) instant setup | B7: A1 | C7: 1 | D7: en
A8: Hi everyone! We are PSP RV-AXIS. Our solutions: RUB OST (high-risk player payments | low-risk salary project) 🇷🇺 CIS 🇰🇿🇰🇬🇺🇿🇦🇿 KRW 🇰🇷 CNY 🇨🇳 AUD 🇦🇺 and others. We are happy to discuss cooperation. | B8: A1 | C8: 1 | D8: en
A9: 1. Пригласила @kamillas2p 2. Кратко о себе: - имя: Ирина - должность Head of BizDev - PSP, NDA | B9: A1 | C9: 1 | D9: ru
A10: ❤️[**COLIBRIX ONE**](https://colibrix.one/) — платежная инфраструктура для digital-бизнеса **Что предлагает **[**COLIBRIX ONE**](https://t.me/colibrixonenews)**:** 🏧 Эквайринг в 130+ странах 🏧 Мультивалютные счета с именным IBAN 🏧 Переводы через SEPA, SEPA Instant и SWIFT 🏧 Мгновенный выпуск виртуальных карт с собственными BIN-номерами и гибким управлением доступами внутри команды 🚀Агентские аккаунты Google и Facebook Давайте знакомиться и сотрудничать! #ggate_tbilisi | B10: A1 | C10: 1 | D10: ru
A11: We are Betixpay, a leading global payment service provider (PSP) specializing in high-growth and high-risk markets Vietnam: Native VietQR (Supports all local E-wallets) India: UPI Intent (Quasi&Native) / P2P Pakistan: JazzCash / Easypaisa High success rates. Direct onboarding. 24/7 tech&operation support. Feel free to DM me if relevant | B11: A1 | C11: 1 | D11: en
A12: #Selling #psp P**ayments Solutions** API & Checkout Page back-office **dashboard** | B12: A1 | C12: 1 | D12: en
A13: Всем привет! Я Адам, представитель Exotic PSP. У нас есть платежные решения на CIS, ASIA, LATAM и MENA. Если есть предложения - пишите в лс, обсудим! Будем рады новым партнерам и знакомствам на конфе🤝 *рассматриваем фиат, Т+0, баланс в USDT #Gmatch | B13: A1 | C13: 1 | D13: ru
... A234: ☑️ **Подключение к Cube** 🙈 🔮**C2C / СБП** 🔴от 1к до 5к ➡️ 15% 🔴до 10к ➡️ 13% 🦋 **МЕЛКОЧЕК** 🔴 до 1к ➡️ 17% ☠️ **КОНТР-АГЕНТЫ** ➡️ 10% 📝**QR НСПК** 🔴до 5к ➡️ 16% 🔴от 5к ➡️ 13% ✍️огромные объемы трафика✍️ 🛒 **ЯНДЕКС ЧАЕВЫЕ** ➡️ 13% ✈️ **МОБКОМ** 🔴до 1к ➡️ 15% 🔴от 1к ➡️ 15% 🔴Выход ➡️ 2% 📃(Рапира, средн.по стакану) 👻БТ out ➡️ 2% 🪭OCT out ➡️ 1% 🌐 **ТРАНСГРАН** ➡️ 7% 👑**Локальный трафик****➖** 🇦🇿 Азербайджан ➡️ 5/1,5% 🇦🇷 Аргентина ➡️ 4/1% 🇧🇷 Бразилия ➡️ 0,5/0,5% 🇪🇬 Египет ➡️ 5/2% 🇰🇿 Казахстан ➡️ 7/2% 🇰🇬 Кыргызстан ➡️ 4/1% 🇲🇩 Молдова ➡️ 5/1,5% 🇰🇷Южная Корея ➡️ 6/1% 🇹🇷 Турция ➡️ 5/1,5% 🇺🇿 Узбекистан ➡️ 1.5/2 🕷️Страховой депозит: 500$ 🔗Апелляционный депозит: 500$ 💬За подключением в лс - ☑️ **Подключение к Cube** 🙈 🔮**C2C / СБП** 🔴от 1к до 5к ➡️ 15% 🔴до 10к ➡️ 13% 🦋 **МЕЛКОЧЕК** 🔴 до 1к ➡️ 17% ☠️ **КОНТР-АГЕНТЫ** ➡️ 10% 📝**QR НСПК** 🔴до 5к ➡️ 16% 🔴от 5к ➡️ 13% ✍️огромные объемы трафика✍️ 🛒 **ЯНДЕКС ЧАЕВЫЕ** ➡️ 13% ✈️ **МОБКОМ** 🔴до 1к ➡️ 15% 🔴от 1к ➡️ 15% 🔴Выход ➡️ 2% 📃(Рапира, средн.по стакану) 👻БТ out ➡️ 2% 🪭OCT out ➡️ 1% 🌐 **ТРАНСГРАН** ➡️ 7% 👑**Локальный трафик****➖** 🇦🇿 Азербайджан ➡️ 5/1,5% 🇦🇷 Аргентина ➡️ 4/1% 🇧🇷 Бразилия ➡️ 0,5/0,5% 🇪🇬 Египет ➡️ 5/2% 🇰🇿 Казахстан ➡️ 7/2% 🇰🇬 Кыргызстан ➡️ 4/1% 🇲🇩 Молдова ➡️ 5/1,5% 🇰🇷Южная Корея ➡️ 6/1% 🇹🇷 Турция ➡️ 5/1,5% 🇺🇿 Узбекистан ➡️ 1.5/2 🕷️Страховой депозит: 500$ 🔗Апелляционный депозит: 500$ 💬За подключением в лс - rezhunozhem Butterflly_Knife | B234: B-1 | C234: 0 | D234: ru

Sheet Саммари
B1: count | C1: out of | D1: remains | E1: among them ru | F1: among them en | H1: null by rows | I1: text | J1: group | K1: label | L1: lang
A2: A1 | B2: =COUNTIFS(Таблиця1[text], "<>", Таблиця1[group], A2) -> 20 | C2: =COUNTIF(Таблиця1[group],Саммари!A2) -> 20 | D2: =C2-B2 -> 0 | E2: =COUNTIFS(Таблиця1[text], "<>", Таблиця1[group], A2, Таблиця1[lang], "ru") -> 8 | F2: =COUNTIFS(Таблиця1[text], "<>", Таблиця1[group], A2, Таблиця1[lang], "en") -> 12 | I2: =COUNTBLANK(Таблиця1[text]) -> 0 | J2: =COUNTBLANK(Таблиця1[group]) -> 0 | K2: =COUNTBLANK(Таблиця1[label]) -> 0 | L2: =COUNTBLANK(Таблиця1[lang]) -> 0
A3: A2 | B3: =COUNTIFS(Таблиця1[text], "<>", Таблиця1[group], A3) -> 30 | C3: =COUNTIF(Таблиця1[group],Саммари!A3) -> 30 | D3: =C3-B3 -> 0 | E3: =COUNTIFS(Таблиця1[text], "<>", Таблиця1[group], A3, Таблиця1[lang], "ru") -> 11 | F3: =COUNTIFS(Таблиця1[text], "<>", Таблиця1[group], A3, Таблиця1[lang], "en") -> 19
A4: B1 | B4: =COUNTIFS(Таблиця1[text], "<>", Таблиця1[group], A4) -> 30 | C4: =COUNTIF(Таблиця1[group],Саммари!A4) -> 30 | D4: =C4-B4 -> 0 | E4: =COUNTIFS(Таблиця1[text], "<>", Таблиця1[group], A4, Таблиця1[lang], "ru") -> 21 | F4: =COUNTIFS(Таблиця1[text], "<>", Таблиця1[group], A4, Таблиця1[lang], "en") -> 9
A5: B2 | B5: =COUNTIFS(Таблиця1[text], "<>", Таблиця1[group], A5) -> 15 | C5: =COUNTIF(Таблиця1[group],Саммари!A5) -> 15 | D5: =C5-B5 -> 0 | E5: =COUNTIFS(Таблиця1[text], "<>", Таблиця1[group], A5, Таблиця1[lang], "ru") -> 15 | F5: =COUNTIFS(Таблиця1[text], "<>", Таблиця1[group], A5, Таблиця1[lang], "en") -> 0
A6: B3 | B6: =COUNTIFS(Таблиця1[text], "<>", Таблиця1[group], A6) -> 25 | C6: =COUNTIF(Таблиця1[group],Саммари!A6) -> 25 | D6: =C6-B6 -> 0 | E6: =COUNTIFS(Таблиця1[text], "<>", Таблиця1[group], A6, Таблиця1[lang], "ru") -> 15 | F6: =COUNTIFS(Таблиця1[text], "<>", Таблиця1[group], A6, Таблиця1[lang], "en") -> 10
A7: B4 | B7: =COUNTIFS(Таблиця1[text], "<>", Таблиця1[group], A7) -> 3 | C7: =COUNTIF(Таблиця1[group],Саммари!A7) -> 3 | D7: =C7-B7 -> 0 | E7: =COUNTIFS(Таблиця1[text], "<>", Таблиця1[group], A7, Таблиця1[lang], "ru") -> 2 | F7: =COUNTIFS(Таблиця1[text], "<>", Таблиця1[group], A7, Таблиця1[lang], "en") -> 1
A8: B-1 | B8: =COUNTIFS(Таблиця1[text], "<>", Таблиця1[group], A8) -> 10 | C8: =COUNTIF(Таблиця1[group],Саммари!A8) -> 10 | D8: =C8-B8 -> 0 | E8: =COUNTIFS(Таблиця1[text], "<>", Таблиця1[group], A8, Таблиця1[lang], "ru") -> 10 | F8: =COUNTIFS(Таблиця1[text], "<>", Таблиця1[group], A8, Таблиця1[lang], "en") -> 0
A11: A0 | B11: =COUNTIFS(Таблиця1[text], "<>", Таблиця1[group], A11) -> 69 | E11: =COUNTIFS(Таблиця1[text], "<>", Таблиця1[group], A11, Таблиця1[lang], "ru") -> 24 | F11: =COUNTIFS(Таблиця1[text], "<>", Таблиця1[group], A11, Таблиця1[lang], "en") -> 45
A12: B0 | B12: =COUNTIFS(Таблиця1[text], "<>", Таблиця1[group], A12) -> 31 | E12: =COUNTIFS(Таблиця1[text], "<>", Таблиця1[group], A12, Таблиця1[lang], "ru") -> 17 | F12: =COUNTIFS(Таблиця1[text], "<>", Таблиця1[group], A12, Таблиця1[lang], "en") -> 14
A13: sum | B13: =SUM(B2:B12) -> 233 | C13: =SUM(C2:C12) -> 133 | D13: =SUM(D2:D12) -> 0 | E13: =SUM(E2:E12) -> 123 | F13: =SUM(F2:F12) -> 110

Sheet То что идет на раг
A1: {=_xlfn._xlws.FILTER(Таблиця1[], (Таблиця1[group]<>"A0") * (Таблиця1[group]<>"B0"))} -> #Selling #Payment Kunga — licensed PSP 89% approval rate | Any industry | Fast Onboarding | T+0 **Local Accounts:** EEUU 🇺🇸, EU (LUX) 🇪🇺, UK 🇬🇧, MX 🇲🇽, CO 🇨🇴, BRA (PIX) 🇧🇷 , AR 🇦🇷 SEPA / SWIFT | B1: A1 | C1: 1 | D1: en
A2: #selling #Payment Psp for FTD! Ftd details EU Retention iban solution De iban ( local),Gb,LU,LT, viban FR | B2: A1 | C2: 1 | D2: en
A3: #selling #Payment Psp for ftds! 90%+ approval - au, NZ, eu and more 👌 Weekly settlements , instant setup✅✅✅ DM for more information‼️ | B3: A1 | C3: 1 | D3: en
A4: Всем привет! #Gmatch Меня зовут Арда, я сооснователь платежного решения Flux Finans. Мы предоставляем стабильные платежные решения для турецкого рынка с минимальными чеками 100/250/500/1000 TL и Conversion Rate 92,7–94,6%. На GGate будем рады познакомиться с мерчантами, PSP-провайдерами и агентами для долгосрочного сотрудничества. Для новых партнеров с конференции — специальные условия и дополнительная скидка. Пишите в личные сообщения, до встречи! | B4: A1 | C4: 1 | D4: ru
A5: Всем привет! Мы предоставляем стабильные платежные решения для турецкого рынка с минимальными чеками: 100 TL (индивидуальный запрос) 500 TL 1000 TL Conversion Rate 92,7–94,6%. Пишите в личные сообщения! | B5: A1 | C5: 1 | D5: ru
A6: #selling worldwide tier 1 psp good approve rate many local apms (europe asia africa latam) instant setup | B6: A1 | C6: 1 | D6: en
A7: Hi everyone! We are PSP RV-AXIS. Our solutions: RUB OST (high-risk player payments | low-risk salary project) 🇷🇺 CIS 🇰🇿🇰🇬🇺🇿🇦🇿 KRW 🇰🇷 CNY 🇨🇳 AUD 🇦🇺 and others. We are happy to discuss cooperation. | B7: A1 | C7: 1 | D7: en
A8: 1. Пригласила @kamillas2p 2. Кратко о себе: - имя: Ирина - должность Head of BizDev - PSP, NDA | B8: A1 | C8: 1 | D8: ru
A9: ❤️[**COLIBRIX ONE**](https://colibrix.one/) — платежная инфраструктура для digital-бизнеса **Что предлагает **[**COLIBRIX ONE**](https://t.me/colibrixonenews)**:** 🏧 Эквайринг в 130+ странах 🏧 Мультивалютные счета с именным IBAN 🏧 Переводы через SEPA, SEPA Instant и SWIFT 🏧 Мгновенный выпуск виртуальных карт с собственными BIN-номерами и гибким управлением доступами внутри команды 🚀Агентские аккаунты Google и Facebook Давайте знакомиться и сотрудничать! #ggate_tbilisi | B9: A1 | C9: 1 | D9: ru
A10: We are Betixpay, a leading global payment service provider (PSP) specializing in high-growth and high-risk markets Vietnam: Native VietQR (Supports all local E-wallets) India: UPI Intent (Quasi&Native) / P2P Pakistan: JazzCash / Easypaisa High success rates. Direct onboarding. 24/7 tech&operation support. Feel free to DM me if relevant | B10: A1 | C10: 1 | D10: en
A11: #Selling #psp P**ayments Solutions** API & Checkout Page back-office **dashboard** | B11: A1 | C11: 1 | D11: en
A12: Всем привет! Я Адам, представитель Exotic PSP. У нас есть платежные решения на CIS, ASIA, LATAM и MENA. Если есть предложения - пишите в лс, обсудим! Будем рады новым партнерам и знакомствам на конфе🤝 *рассматриваем фиат, Т+0, баланс в USDT #Gmatch | B12: A1 | C12: 1 | D12: ru
A13: Привет, GGate 🔥 Меня зовут Дарья @DariaSpayz, я представляю SPAYZ.io — агрегатор платежных провайдеров для iGaming и Forex вертикалей с опытом работы 10+ лет на рынке Мы предлагаем: • прием/выплату платежей в локальной валюте • стабильный процессинг и быстрый сетлмент без скрытых комиссий • API-интеграцию под ваш технический стек • индивидуальные условия и тарифы для каждого клиента • быстрый онбординг и поддержку 24/7 **Азия** - 🇲🇾 Малайзия, 🇵🇭 Филиппины, 🇮🇩 Индонезия, 🇻🇳 Вьетнам, 🇸🇬 Сингапур, 🇵🇰 Пакистан, 🇧🇩 Бангладеш , 🇹🇭 Таилан, 🇰🇷 Южная Корея, 🇮🇳 Индия, 🇲🇳 Монголия **Африка** - 🇳🇬 Нигерия, 🇰🇪 Кения, 🇬🇭 Гана, 🇨🇩 Конго, 🇿🇦 Южная Африка, 🇹🇿 Танзания, 🇿🇲 Замбия, 🇨🇲 Камерун **Mena** - 🇦🇪 ОАЭ Буду рада обсудить сотрудничество 🤍 | B13: A1 | C13: 1 | D13: ru
... A133: ☑️ **Подключение к Cube** 🙈 🔮**C2C / СБП** 🔴от 1к до 5к ➡️ 15% 🔴до 10к ➡️ 13% 🦋 **МЕЛКОЧЕК** 🔴 до 1к ➡️ 17% ☠️ **КОНТР-АГЕНТЫ** ➡️ 10% 📝**QR НСПК** 🔴до 5к ➡️ 16% 🔴от 5к ➡️ 13% ✍️огромные объемы трафика✍️ 🛒 **ЯНДЕКС ЧАЕВЫЕ** ➡️ 13% ✈️ **МОБКОМ** 🔴до 1к ➡️ 15% 🔴от 1к ➡️ 15% 🔴Выход ➡️ 2% 📃(Рапира, средн.по стакану) 👻БТ out ➡️ 2% 🪭OCT out ➡️ 1% 🌐 **ТРАНСГРАН** ➡️ 7% 👑**Локальный трафик****➖** 🇦🇿 Азербайджан ➡️ 5/1,5% 🇦🇷 Аргентина ➡️ 4/1% 🇧🇷 Бразилия ➡️ 0,5/0,5% 🇪🇬 Египет ➡️ 5/2% 🇰🇿 Казахстан ➡️ 7/2% 🇰🇬 Кыргызстан ➡️ 4/1% 🇲🇩 Молдова ➡️ 5/1,5% 🇰🇷Южная Корея ➡️ 6/1% 🇹🇷 Турция ➡️ 5/1,5% 🇺🇿 Узбекистан ➡️ 1.5/2 🕷️Страховой депозит: 500$ 🔗Апелляционный депозит: 500$ 💬За подключением в лс - ☑️ **Подключение к Cube** 🙈 🔮**C2C / СБП** 🔴от 1к до 5к ➡️ 15% 🔴до 10к ➡️ 13% 🦋 **МЕЛКОЧЕК** 🔴 до 1к ➡️ 17% ☠️ **КОНТР-АГЕНТЫ** ➡️ 10% 📝**QR НСПК** 🔴до 5к ➡️ 16% 🔴от 5к ➡️ 13% ✍️огромные объемы трафика✍️ 🛒 **ЯНДЕКС ЧАЕВЫЕ** ➡️ 13% ✈️ **МОБКОМ** 🔴до 1к ➡️ 15% 🔴от 1к ➡️ 15% 🔴Выход ➡️ 2% 📃(Рапира, средн.по стакану) 👻БТ out ➡️ 2% 🪭OCT out ➡️ 1% 🌐 **ТРАНСГРАН** ➡️ 7% 👑**Локальный трафик****➖** 🇦🇿 Азербайджан ➡️ 5/1,5% 🇦🇷 Аргентина ➡️ 4/1% 🇧🇷 Бразилия ➡️ 0,5/0,5% 🇪🇬 Египет ➡️ 5/2% 🇰🇿 Казахстан ➡️ 7/2% 🇰🇬 Кыргызстан ➡️ 4/1% 🇲🇩 Молдова ➡️ 5/1,5% 🇰🇷Южная Корея ➡️ 6/1% 🇹🇷 Турция ➡️ 5/1,5% 🇺🇿 Узбекистан ➡️ 1.5/2 🕷️Страховой депозит: 500$ 🔗Апелляционный депозит: 500$ 💬За подключением в лс - rezhunozhem Butterflly_Knife | B133: B-1 | C133: 0 | D133: ru
